pretalx_api/__init__.py
pretalx_api/api.py
pretalx_api/exceptions.py
pretalx_api/filters.py
pretalx_api/metadata.py
pyPretalxAPI-1.0.1.dist-info/LICENSE
pyPretalxAPI-1.0.1.dist-info/METADATA
pyPretalxAPI-1.0.1.dist-info/WHEEL
pyPretalxAPI-1.0.1.dist-info/top_level.txt
pyPretalxAPI-1.0.1.dist-info/RECORD
